engcom/__init__.py
engcom/data.py
engcom/filter.lua
engcom/models.py
engcom/pandoc_reference.docx
engcom/publication.py
engcom/publish.py
engcom/show.py
engcom/simplification.py
engcom/tufte.py
engcom-0.1.34.dist-info/LICENSE
engcom-0.1.34.dist-info/METADATA
engcom-0.1.34.dist-info/WHEEL
engcom-0.1.34.dist-info/entry_points.txt
engcom-0.1.34.dist-info/RECORD
